vhdmmio/__init__.py
vhdmmio/__main__.py
vhdmmio/template.py
vhdmmio/utils.py
vhdmmio/version.py
vhdmmio/config/__init__.py
vhdmmio/config/__main__.py
vhdmmio/config/conditions.py
vhdmmio/config/entity.py
vhdmmio/config/features.py
vhdmmio/config/field.py
vhdmmio/config/interface.py
vhdmmio/config/internal_io.py
vhdmmio/config/interrupt.py
vhdmmio/config/metadata.py
vhdmmio/config/permissions.py
vhdmmio/config/register_file.py
vhdmmio/config/subaddress.py
vhdmmio/config/behavior/__init__.py
vhdmmio/config/behavior/axi.py
vhdmmio/config/behavior/constant.py
vhdmmio/config/behavior/control.py
vhdmmio/config/behavior/counter.py
vhdmmio/config/behavior/custom.py
vhdmmio/config/behavior/flag.py
vhdmmio/config/behavior/interrupt.py
vhdmmio/config/behavior/memory.py
vhdmmio/config/behavior/primitive.py
vhdmmio/config/behavior/registry.py
vhdmmio/config/behavior/request.py
vhdmmio/config/behavior/status.py
vhdmmio/config/behavior/stream.py
vhdmmio/configurable/__init__.py
vhdmmio/configurable/checked.py
vhdmmio/configurable/choice.py
vhdmmio/configurable/configurable.py
vhdmmio/configurable/listconfig.py
vhdmmio/configurable/loader.py
vhdmmio/configurable/select.py
vhdmmio/configurable/subconfig.py
vhdmmio/configurable/utils.py
vhdmmio/core/__init__.py
vhdmmio/core/address.py
vhdmmio/core/bitrange.py
vhdmmio/core/block.py
vhdmmio/core/defer_tag.py
vhdmmio/core/field.py
vhdmmio/core/field_descriptor.py
vhdmmio/core/interface_options.py
vhdmmio/core/internal.py
vhdmmio/core/interrupt.py
vhdmmio/core/logical_register.py
vhdmmio/core/namespace.py
vhdmmio/core/register_file.py
vhdmmio/core/resources.py
vhdmmio/core/subaddress.py
vhdmmio/core/behavior/__init__.py
vhdmmio/core/behavior/axi.py
vhdmmio/core/behavior/base.py
vhdmmio/core/behavior/custom.py
vhdmmio/core/behavior/interrupt.py
vhdmmio/core/behavior/primitive.py
vhdmmio/core/mixins/__init__.py
vhdmmio/core/mixins/accessed.py
vhdmmio/core/mixins/configured.py
vhdmmio/core/mixins/named.py
vhdmmio/core/mixins/shaped.py
vhdmmio-0.0.3.dist-info/LICENSE
vhdmmio-0.0.3.dist-info/METADATA
vhdmmio-0.0.3.dist-info/WHEEL
vhdmmio-0.0.3.dist-info/entry_points.txt
vhdmmio-0.0.3.dist-info/top_level.txt
vhdmmio-0.0.3.dist-info/RECORD
