Metadata-Version: 2.1
Name: vhdmmio
Version: 0.0.3
Summary: VHDL code generator for AXI4-lite compatible memory-mapped I/O (MMIO)register files and bus infrastructure.
Home-page: https://github.com/abs-tudelft/vhdmmio
Author: Jeroen van Straten
Author-email: j.vanstraten-1@tudelft.nl
License: Apache
Project-URL: Source, https://github.com/abs-tudelft/vhdmmio
Keywords: vhdl mmio registers generator
Platform: UNKNOWN
Classifier: Development Status :: 3 - Alpha
Classifier: Intended Audience :: Developers
Classifier: Topic :: Software Development :: Code Generators
Classifier: License :: OSI Approved :: Apache Software License
Classifier: Programming Language :: Python :: 3
Requires-Python: >=3.5
Requires-Dist: markdown2
Requires-Dist: pyyaml
